fastapi_chat/__init__.py
fastapi_chat/run.py
fastapi_chat/chat/__init__.py
fastapi_chat/chat/app.py
fastapi_chat/chat/manager.py
fastapi_chat/chat/settings.py
jellyfish_chat-0.0.3.dist-info/LICENSE
jellyfish_chat-0.0.3.dist-info/METADATA
jellyfish_chat-0.0.3.dist-info/WHEEL
jellyfish_chat-0.0.3.dist-info/entry_points.txt
jellyfish_chat-0.0.3.dist-info/top_level.txt
jellyfish_chat-0.0.3.dist-info/RECORD
