Metadata-Version: 2.1
Name: jellyfish-chat
Version: 0.0.3
Summary: FastAPI microservice for chatting
Home-page: https://gitlab.com/jellyfish-sdk/fastapi-chat
Author: Jellyfish
Author-email: danil.vasiliuk@gmail.com
License: BSD-3-Clause  # Example license
Platform: UNKNOWN
Classifier: Environment :: Web Environment
Classifier: Intended Audience :: Developers
Classifier: License :: OSI Approved :: MIT License
Classifier: Operating System :: OS Independent
Classifier: Programming Language :: Python
Classifier: Programming Language :: Python :: 3
Classifier: Programming Language :: Python :: 3 :: Only
Classifier: Topic :: Internet :: WWW/HTTP
Classifier: Topic :: Internet :: WWW/HTTP :: Dynamic Content
Requires-Python: >=3.8
License-File: LICENSE
Requires-Dist: fastapi (>=0.70.0)
Requires-Dist: httpx (>=0.13.3)
Requires-Dist: uvicorn (>=0.11.5)
Requires-Dist: websockets (>=8.1)
Requires-Dist: sentry-sdk (>=1.3.0)
Requires-Dist: broadcaster (>=0.2.0)
Requires-Dist: asyncio-redis (>=0.16.0)
